movement_2d/__init__.py
movement_2d-1.1.1.dist-info/AUTHORS
movement_2d-1.1.1.dist-info/LICENSE
movement_2d-1.1.1.dist-info/METADATA
movement_2d-1.1.1.dist-info/WHEEL
movement_2d-1.1.1.dist-info/pbr.json
movement_2d-1.1.1.dist-info/top_level.txt
movement_2d-1.1.1.dist-info/RECORD
