Metadata-Version: 2.1
Name: movement-2d
Version: 1.1.1
Summary: Various functions relating to 2d movement.
Home-page: UNKNOWN
Author: Chris Norman
Author-email: chris.norman2@googlemail.com
License: MPL
Platform: UNKNOWN
